{"index":307,"components":["FE","MN","VA"],"conditions":{"N":1,"P":101325,"T":1273.15,"X_MN":0.13135705},"reference":"Esser1925","disabled":false,"model":"martensite_start","inputs":{"martensite_start":427.5124161074,"martensite_type":"epsilon","PAGS":null,"parent_phase":"gamma","predicted_type":false,"solutionizing_temperature":1273.15},"outputs":{"calculation_error":false,"DG":133.6655688579,"error":-16.4177331703,"error_message":[],"LC_martensite_start":443.9301492777,"PAGS_energy":0.0,"solutioning_conditions":{"N":1,"P":101325,"T":1273.15,"X_MN":0.13135705},"solutionizing_phases":["FCC_A1","",""]}}