{"index":530,"components":["FE","MN","SI","VA"],"conditions":{"N":1,"P":101325,"T":1273.15,"X_MN":0.1725,"X_SI":0.0101},"reference":"Ishida1974a","disabled":false,"model":"martensite_start","inputs":{"martensite_start":409.15,"martensite_type":"epsilon","PAGS":null,"parent_phase":"gamma","predicted_type":false,"solutionizing_temperature":1273.15},"outputs":{"calculation_error":false,"DG":202.0117202477,"error":-11.594435463,"error_message":[],"LC_martensite_start":420.744435463,"PAGS_energy":0.0,"solutioning_conditions":{"N":1,"P":101325,"T":1273.15,"X_MN":0.1725,"X_SI":0.0101},"solutionizing_phases":["FCC_A1","","",""]}}