{"index":87,"components":["C","CR","FE","MN","MO","SI","VA"],"conditions":{"N":1,"P":101325,"T":1273.15,"X_C":0.0055245931,"X_CR":0.0957103949,"X_MN":0.0070455063,"X_MO":0.005763518,"X_SI":0.0059064491},"reference":"Atkins1980","disabled":false,"model":"martensite_start","inputs":{"martensite_start":601.0,"martensite_type":"lath","PAGS":null,"parent_phase":"gamma","predicted_type":true,"solutionizing_temperature":1273.15},"outputs":{"calculation_error":false,"DG":2339.8916150894,"error":6.1553758621,"error_message":[],"LC_martensite_start":594.8446241379,"PAGS_energy":0.0,"solutioning_conditions":{"N":1,"P":101325,"T":1273.15,"X_C":0.0055245931,"X_CR":0.0957103949,"X_MN":0.0070455063,"X_MO":0.005763518,"X_SI":0.0059064491},"solutionizing_phases":["FCC_A1","CHI_A12","BCC_A2","","","",""]}}