{"index":435,"components":["C","FE","MN","P","S","SI","VA"],"conditions":{"N":1,"P":101325,"T":1373.15,"X_C":0.0064400762,"X_MN":0.1438116685,"X_P":0.000784856,"X_S":0.0008787599,"X_SI":0.0051147272},"reference":"Hadfield1927","disabled":false,"model":"martensite_start","inputs":{"martensite_start":379.15,"martensite_type":"epsilon","PAGS":null,"parent_phase":"gamma","predicted_type":true,"solutionizing_temperature":1373.15},"outputs":{"calculation_error":false,"DG":349.9345764623,"error":-18.2077883816,"error_message":[],"LC_martensite_start":397.3577883816,"PAGS_energy":0.0,"solutioning_conditions":{"N":1,"P":101325,"T":1373.15,"X_C":0.0064400762,"X_MN":0.1438116685,"X_P":0.000784856,"X_S":0.0008787599,"X_SI":0.0051147272},"solutionizing_phases":["LIQUID","FCC_A1","","","","",""]}}