{"index":702,"components":["C","CR","FE","MN","SI","VA"],"conditions":{"N":1,"P":101325,"T":1533.15,"X_C":0.0227543661,"X_CR":0.0103019245,"X_MN":0.0031837564,"X_SI":0.0052546605},"reference":"Payson1944","disabled":false,"model":"martensite_start","inputs":{"martensite_start":585.9277777778,"martensite_type":"plate","PAGS":null,"parent_phase":"gamma","predicted_type":false,"solutionizing_temperature":1533.15},"outputs":{"calculation_error":false,"DG":2520.803597652,"error":-17.2319430745,"error_message":[],"LC_martensite_start":603.1597208523,"PAGS_energy":0.0,"solutioning_conditions":{"N":1,"P":101325,"T":1533.15,"X_C":0.0227543661,"X_CR":0.0103019245,"X_MN":0.0031837564,"X_SI":0.0052546605},"solutionizing_phases":["FCC_A1","","","","",""]}}