{"index":820,"components":["CO","FE","NI","VA"],"conditions":{"N":1,"P":101325,"T":1273.15,"X_CO":0.3334822629,"X_NI":0.2014353811},"reference":"Shibata2006","disabled":false,"model":"martensite_start","inputs":{"martensite_start":497.0,"martensite_type":"plate","PAGS":null,"parent_phase":"gamma","predicted_type":false,"solutionizing_temperature":1273.15},"outputs":{"calculation_error":false,"DG":1377.0351497983,"error":80.4396274567,"error_message":["Solution phase is Fe-poor."],"LC_martensite_start":416.5603725433,"PAGS_energy":0.0,"solutioning_conditions":{"N":1,"P":101325,"T":1273.15,"X_CO":0.3334822629,"X_NI":0.2014353811},"solutionizing_phases":["FCC_A1","","",""]}}