{"index":675,"components":["FE","VA"],"conditions":{"N":1,"P":101325,"T":1273.15},"reference":"Mirzayev1981","disabled":false,"model":"martensite_start","inputs":{"martensite_start":697.1173113951,"martensite_type":"plate","PAGS":null,"parent_phase":"gamma","predicted_type":false,"solutionizing_temperature":1273.15},"outputs":{"calculation_error":false,"DG":2087.0652499583,"error":0.2602781557,"error_message":[],"LC_martensite_start":696.8570332394,"PAGS_energy":0.0,"solutioning_conditions":{"N":1,"P":101325,"T":1273.15},"solutionizing_phases":["FCC_A1",""]}}